randcolor/__init__.py
randcolor/menu.py
randcolor-1.1.0.data/scripts/menu.py
randcolor-1.1.0.dist-info/METADATA
randcolor-1.1.0.dist-info/WHEEL
randcolor-1.1.0.dist-info/entry_points.txt
randcolor-1.1.0.dist-info/top_level.txt
randcolor-1.1.0.dist-info/RECORD
