Metadata-Version: 2.1
Name: randcolor
Version: 1.1.0
Summary: Make a map
Home-page: https://github.com/FuryBaM/randcolor
Author: FuryBaM
Author-email: furybam@gmail.com
License: UNKNOWN
Platform: UNKNOWN
Requires-Dist: Pillow
Requires-Dist: tqdm
Requires-Dist: numpy
